odoo10_addon_project_issue_timesheet_time_control-10.0.1.1.0-py2.7-nspkg.pth
odoo/addons/project_issue_timesheet_time_control/README.rst
odoo/addons/project_issue_timesheet_time_control/__init__.py
odoo/addons/project_issue_timesheet_time_control/__manifest__.py
odoo/addons/project_issue_timesheet_time_control/i18n/ar.po
odoo/addons/project_issue_timesheet_time_control/i18n/ca.po
odoo/addons/project_issue_timesheet_time_control/i18n/de.po
odoo/addons/project_issue_timesheet_time_control/i18n/el.po
odoo/addons/project_issue_timesheet_time_control/i18n/es.po
odoo/addons/project_issue_timesheet_time_control/i18n/es_CR.po
odoo/addons/project_issue_timesheet_time_control/i18n/es_MX.po
odoo/addons/project_issue_timesheet_time_control/i18n/es_VE.po
odoo/addons/project_issue_timesheet_time_control/i18n/fi.po
odoo/addons/project_issue_timesheet_time_control/i18n/fr.po
odoo/addons/project_issue_timesheet_time_control/i18n/gl.po
odoo/addons/project_issue_timesheet_time_control/i18n/hr.po
odoo/addons/project_issue_timesheet_time_control/i18n/hr_HR.po
odoo/addons/project_issue_timesheet_time_control/i18n/hu.po
odoo/addons/project_issue_timesheet_time_control/i18n/it.po
odoo/addons/project_issue_timesheet_time_control/i18n/ja.po
odoo/addons/project_issue_timesheet_time_control/i18n/lt.po
odoo/addons/project_issue_timesheet_time_control/i18n/lv.po
odoo/addons/project_issue_timesheet_time_control/i18n/mk.po
odoo/addons/project_issue_timesheet_time_control/i18n/mn.po
odoo/addons/project_issue_timesheet_time_control/i18n/nb.po
odoo/addons/project_issue_timesheet_time_control/i18n/nl.po
odoo/addons/project_issue_timesheet_time_control/i18n/nl_NL.po
odoo/addons/project_issue_timesheet_time_control/i18n/pl.po
odoo/addons/project_issue_timesheet_time_control/i18n/pt.po
odoo/addons/project_issue_timesheet_time_control/i18n/pt_BR.po
odoo/addons/project_issue_timesheet_time_control/i18n/pt_PT.po
odoo/addons/project_issue_timesheet_time_control/i18n/ro.po
odoo10_addon_project_issue_timesheet_time_control-10.0.1.1.0.dist-info/DESCRIPTION.rst
odoo10_addon_project_issue_timesheet_time_control-10.0.1.1.0.dist-info/METADATA
odoo10_addon_project_issue_timesheet_time_control-10.0.1.1.0.dist-info/RECORD
odoo10_addon_project_issue_timesheet_time_control-10.0.1.1.0.dist-info/WHEEL
odoo10_addon_project_issue_timesheet_time_control-10.0.1.1.0.dist-info/metadata.json
odoo10_addon_project_issue_timesheet_time_control-10.0.1.1.0.dist-info/namespace_packages.txt
odoo10_addon_project_issue_timesheet_time_control-10.0.1.1.0.dist-info/top_level.txt
